sentspace/Sentence.py
sentspace/__init__.py
sentspace/__main__.py
sentspace/embedding/.gitkeep
sentspace/embedding/__init__.py
sentspace/embedding/utils.py
sentspace/lexical/.gitkeep
sentspace/lexical/__init__.py
sentspace/lexical/sanity_checks.py
sentspace/lexical/utils.py
sentspace/semantic/.gitkeep
sentspace/syntax/.gitkeep
sentspace/syntax/README.md
sentspace/syntax/__init__.py
sentspace/syntax/compute_tree_dlt_left_corner.py
sentspace/syntax/features.py
sentspace/syntax/utils/__init__.py
sentspace/syntax/utils/calcDLT.py
sentspace/syntax/utils/calcEmbd.py
sentspace/syntax/utils/dlt.sh
sentspace/syntax/utils/leftcorner.sh
sentspace/syntax/utils/linetrees2mlpsemprocdecpars
sentspace/syntax/utils/make-trees-nounary.pl
sentspace/syntax/utils/parse_trees.sh
sentspace/syntax/utils/parser-fullberk
sentspace/syntax/utils/postprocess_trees.sh
sentspace/syntax/utils/printlemmas.py
sentspace/syntax/utils/ptb_tokenizer.sed
sentspace/syntax/utils/tokenize.sh
sentspace/syntax/utils/tree.py
sentspace/utils/.gitkeep
sentspace/utils/__init__.py
sentspace/utils/caching.py
sentspace/utils/io.py
sentspace/utils/misc.py
sentspace/utils/plotting.py
sentspace/utils/s3.py
sentspace/utils/text.py
sentspace/web/.gitkeep
sentspace-0.0.2.dist-info/WHEEL
sentspace-0.0.2.dist-info/METADATA
sentspace-0.0.2.dist-info/RECORD
